{
    "key": "group_65ca55f45368c",
    "title": "Component: Cover Link",
    "fields": [
        {
            "key": "field_63c9c2ae1c476",
            "label": "Enable cover link",
            "name": "enable_cover_link",
            "aria-label": "",
            "type": "true_false",
            "instructions": "This makes the whole of the block a clickable link element.",
            "required": 0,
            "conditional_logic": 0,
            "wrapper": {
                "width": "",
                "class": "",
                "id": ""
            },
            "wpml_cf_preferences": 3,
            "user_roles": [
                "administrator"
            ],
            "message": "",
            "default_value": 0,
            "ui_on_text": "",
            "ui_off_text": "",
            "ui": 1,
            "style": ""
        },
        {
            "key": "field_63c9c2d71c477",
            "label": "Cover link",
            "name": "cover_link",
            "aria-label": "",
            "type": "link",
            "instructions": "",
            "required": 0,
            "conditional_logic": 0,
            "wrapper": {
                "width": "",
                "class": "",
                "id": ""
            },
            "wpml_cf_preferences": 3,
            "user_roles": [
                "administrator"
            ],
            "return_format": "array"
        },
        {
            "key": "field_63d94025b6764",
            "label": "Enable cover link hover effect",
            "name": "enable_cover_link_hover_effect",
            "aria-label": "",
            "type": "true_false",
            "instructions": "",
            "required": 0,
            "conditional_logic": 0,
            "wrapper": {
                "width": "",
                "class": "",
                "id": ""
            },
            "wpml_cf_preferences": 3,
            "user_roles": [
                "administrator"
            ],
            "message": "",
            "default_value": 0,
            "ui_on_text": "",
            "ui_off_text": "",
            "ui": 1,
            "style": ""
        }
    ],
    "location": [
        [
            {
                "param": "post_type",
                "operator": "==",
                "value": "post"
            }
        ]
    ],
    "menu_order": 0,
    "position": "normal",
    "style": "default",
    "label_placement": "left",
    "instruction_placement": "label",
    "hide_on_screen": "",
    "active": false,
    "description": "",
    "show_in_rest": 0,
    "acfe_autosync": [
        "json"
    ],
    "acfml_field_group_mode": "localization",
    "acfe_form": 0,
    "acfe_display_title": "",
    "acfe_meta": "",
    "acfe_note": "",
    "modified": 1746891300
}
