{
    "key": "group_68752075dd831",
    "title": "Block: Market Selector v3",
    "fields": [
        {
            "key": "field_68762d4f6632f",
            "label": "Block Settings",
            "name": "",
            "aria-label": "",
            "type": "tab",
            "instructions": "",
            "required": 0,
            "conditional_logic": 0,
            "wrapper": {
                "width": "",
                "class": "",
                "id": ""
            },
            "wpml_cf_preferences": 3,
            "placement": "top",
            "endpoint": 0,
            "no_preference": 0,
            "selected": 0
        },
        {
            "key": "field_6875207709d8d",
            "label": "Selector Type",
            "name": "selector_type",
            "aria-label": "",
            "type": "radio",
            "instructions": "",
            "required": 0,
            "conditional_logic": 0,
            "wrapper": {
                "width": "",
                "class": "",
                "id": ""
            },
            "wpml_cf_preferences": 3,
            "choices": {
                "__pop-up": "Pop Up",
                "__inline": "Inline"
            },
            "default_value": "__pop-up : Pop Up",
            "return_format": "value",
            "allow_null": 0,
            "other_choice": 0,
            "layout": "vertical",
            "save_other_choice": 0
        },
        {
            "key": "field_6877b0a54f3eb",
            "label": "Heading Text",
            "name": "heading_text",
            "aria-label": "",
            "type": "text",
            "instructions": "",
            "required": 0,
            "conditional_logic": 0,
            "wrapper": {
                "width": "",
                "class": "",
                "id": ""
            },
            "wpml_cf_preferences": 2,
            "default_value": "",
            "maxlength": "",
            "placeholder": "",
            "prepend": "",
            "append": ""
        },
        {
            "key": "field_687910f6aa776",
            "label": "Logo",
            "name": "logo",
            "aria-label": "",
            "type": "image",
            "instructions": "",
            "required": 0,
            "conditional_logic": 0,
            "wrapper": {
                "width": "",
                "class": "",
                "id": ""
            },
            "wpml_cf_preferences": 3,
            "uploader": "",
            "return_format": "id",
            "library": "all",
            "upload_folder": "",
            "acfe_thumbnail": 0,
            "min_width": "",
            "min_height": "",
            "min_size": "",
            "max_width": "",
            "max_height": "",
            "max_size": "",
            "mime_types": "",
            "preview_size": "medium"
        }
    ],
    "location": [
        [
            {
                "param": "block",
                "operator": "==",
                "value": "acf\/market-selector-v3"
            }
        ]
    ],
    "menu_order": 0,
    "position": "normal",
    "style": "default",
    "label_placement": "left",
    "instruction_placement": "label",
    "hide_on_screen": "",
    "active": true,
    "description": "",
    "show_in_rest": 0,
    "acfe_autosync": [
        "json"
    ],
    "acfml_field_group_mode": "localization",
    "acfe_form": 0,
    "acfe_display_title": "",
    "acfe_meta": "",
    "acfe_note": "",
    "modified": 1752848810
}
